{
  "schemaVersion": 1,
  "date": "2026-02-19",
  "difficulty": 6,
  "category": "Greek Gods",
  "shareClueIndex": 7,
  "items": [
    { "answer": "ZEUS",        "clue": "ZS",        "difficulty": 1 },
    { "answer": "HERA",        "clue": "HR",        "difficulty": 2 },
    { "answer": "ARES",        "clue": "RS",        "difficulty": 3 },
    { "answer": "ATHENA",      "clue": "THN",       "difficulty": 4 },
    { "answer": "APOLLO",      "clue": "PLL",       "difficulty": 5 },
    { "answer": "POSEIDON",    "clue": "PSD N", "difficulty": 6 },
    { "answer": "ARTEMIS",     "clue": "RT MS",      "difficulty": 7 },
    { "answer": "HEPHAESTUS",  "clue": "HP HSTS",    "difficulty": 8 }
  ]
}
